[
  {
    "search": {
      "prefix": "this[_0x34a79e(0xb65)][_0x34a79e(0x1024)]())),this['SpawnBoss']();",
      "suffix": "}['SpawnYellowItems']"
    },
    "inject": "dispatchEvent(new CustomEvent('game-init',{detail:{data:_0x1a4126,EnemyGroupClass:_0x5bcca2.default}}))"
  },
  {
    "search": {
      "prefix": "catch(_0x3f71d8){_0x55efa8[_0x35e6a1(0x8dc)]=null;}",
      "suffix": "}"
    },
    "inject": "dispatchEvent(new CustomEvent('phaser-init',{detail:{Info:_0x55efa8}}))"
  },
  {
    "debug": true,
    "search": {
      "prefix": "'OPEN_DEV_TOOLS':!0x1,",
      "suffix": ""
    },
    "inject": "'OPEN_DEV_TOOLS':0x1,"
  }
]
